tensor_parallel/__init__.py
tensor_parallel/autoconfig.py
tensor_parallel/aux_actions.py
tensor_parallel/communications.py
tensor_parallel/config.py
tensor_parallel/cross_device_ops.py
tensor_parallel/dispatch.py
tensor_parallel/factory.py
tensor_parallel/imports.py
tensor_parallel/legacy.py
tensor_parallel/per_device_tensors.py
tensor_parallel/pretrained_model.py
tensor_parallel/shard.py
tensor_parallel/sharding.py
tensor_parallel/slicing_configs.py
tensor_parallel/state_actions.py
tensor_parallel/tensor_parallel.py
tensor_parallel/utils.py
tensor_parallel/wrapper.py
tensor_parallel-2.0.0.dist-info/LICENCE
tensor_parallel-2.0.0.dist-info/METADATA
tensor_parallel-2.0.0.dist-info/WHEEL
tensor_parallel-2.0.0.dist-info/top_level.txt
tensor_parallel-2.0.0.dist-info/RECORD
