Metadata-Version: 2.1
Name: tensor-parallel
Version: 2.0.0
Summary: Automatically shard your large model between multiple GPUs, works without torch.distributed
Home-page: https://github.com/BlackSamorez/tensor_parallel
Author: Andrei Panferov and Yaroslav Lisnyak
Author-email: yalisnyak@nes.com
Project-URL: Bug Tracker, https://github.com/BlackSamorez/tensor_parallel/issues
Classifier: Development Status :: 4 - Beta
Classifier: Intended Audience :: Developers
Classifier: Intended Audience :: Science/Research
Classifier: License :: OSI Approved :: MIT License
Classifier: Programming Language :: Python :: 3
Classifier: Programming Language :: Python :: 3.7
Classifier: Programming Language :: Python :: 3.8
Classifier: Programming Language :: Python :: 3.9
Classifier: Programming Language :: Python :: 3.10
Classifier: Topic :: Scientific/Engineering
Classifier: Topic :: Scientific/Engineering :: Mathematics
Classifier: Topic :: Scientific/Engineering :: Artificial Intelligence
Classifier: Topic :: Software Development
Classifier: Topic :: Software Development :: Libraries
Classifier: Topic :: Software Development :: Libraries :: Python Modules
Requires-Python: >=3.7
License-File: LICENCE
Requires-Dist: torch >=1.11
Requires-Dist: transformers >=4.20.1
Provides-Extra: dev
Requires-Dist: pytest ==6.2.5 ; extra == 'dev'
Requires-Dist: pytest-forked ; extra == 'dev'
Requires-Dist: pytest-asyncio ==0.16.0 ; extra == 'dev'
Requires-Dist: accelerate ==0.20.3 ; extra == 'dev'
Requires-Dist: black ==22.3.0 ; extra == 'dev'
Requires-Dist: isort ==5.10.1 ; extra == 'dev'
Requires-Dist: psutil ; extra == 'dev'
Requires-Dist: peft ==0.3.0 ; extra == 'dev'
Requires-Dist: einops ==0.6.1 ; extra == 'dev'
